{"items_array":[{"a":5,"c":12,"e":"BEST COOL FUNNY GAMES FFG &amp; TOP FUN FREE APP FOR BABY KIDS GIRLS BOYS","g":"15","i":"doodle-moto-hd-free-racing_id548251089","n":"Doodle Moto HD-Free Racing Games for All Girls Boys on iPad iPhone","o":13459,"p":"Free","r":66},{"a":4.5,"c":12,"e":"TreSensa, Inc.","g":"1","i":"vector-runner-remix_id582523218","n":"Vector Runner Remix","o":77,"p":"Free","r":67},{"a":4.5,"c":12,"e":"MoFunZone Inc","g":"15","i":"duck-life-treasure-hunt_id875625142","n":"Duck Life: Treasure Hunt","o":216,"p":"Free","r":68},{"a":4.5,"c":12,"e":"Shiming Huang","g":"6","i":"flying-ghost-fun-free-games_id919434177","n":"Flying Ghost - fun free games for boys &amp; girls nono","o":41,"p":"Free","r":69},{"a":4.5,"c":12,"e":"Shiming Huang","g":"6","i":"fat-bird-top-fun-free-family_id952963581","n":"Fat bird - top fun free family games for kids nono mountain goat","o":71,"p":"Free","r":70},{"a":4,"c":12,"e":"Games Cafe Inc.","g":"6","i":"sallys-spa-lite_id315733642","n":"Sally's Spa Lite","o":194939,"p":"Free","r":71},{"a":4,"c":13,"e":"Blitwise Productions, LLC","g":"5","i":"pocket-tanks_id311544087","n":"Pocket Tanks","o":89763,"p":"Free","r":66},{"a":5,"c":13,"e":"Game Hive Corp.","g":"1","i":"beat-the-boss_id504656060","n":"Beat the Boss","o":232872,"p":"Free","r":67},{"a":4.5,"c":13,"e":"TriggerWave LLC","g":"4","i":"penguin-village_id700772155","n":"Penguin Village","o":1708,"p":"Free","r":68},{"a":5,"c":13,"e":"Mingcan Huang","g":"6","i":"flappy-fire-bird-top-fun-free_id986722026","n":"Flappy Fire Bird - top fun free jump games nono","o":236,"p":"Free","r":69},{"a":5,"c":13,"e":"ICON, LLC","g":"9","i":"all-guess-mortal-kombat-edition_id1015186533","n":"All Guess Mortal Kombat Edition Trivia Logos X Quiz","o":246,"p":"Free","r":70},{"a":4,"c":13,"e":"Tiltan Games (2013) LTD","g":"2","i":"cars-pals-car-truck-train_id657057868","n":"Cars and Pals: Car Truck and Train Jigsaw Puzzle Games for Kids and Toddler","o":228,"p":"Free","r":71},{"a":4.5,"c":14,"e":"NimbleBit LLC","g":"4","i":"tiny-tower-free-city-building_id422667065","n":"Tiny Tower - Free City Building","o":396722,"p":"Free","r":66},{"a":4.5,"c":14,"e":"Ravenous Games Inc.","g":"1","i":"random-heroes-3_id921379745","n":"Random Heroes 3","o":152,"p":"$0.99","r":67},{"a":3.5,"c":14,"e":"GANZ","g":"10","i":"webkinz_id680610650","n":"Webkinz","o":1183,"p":"Free","r":68},{"a":4.5,"c":14,"e":"Simplus Technologies Group, LLC","g":"1","i":"enemy-dawn-wwii-global-conflict_id826266462","n":"Enemy Dawn : WWII Global Conflict Warfare Lite","o":70,"p":"Free","r":69},{"a":4,"c":14,"e":"Tiltan Games (2013) LTD","g":"2","i":"dino-maze-dinosaur-mazes-for_id593083065","n":"Dino Maze - Dinosaur Mazes For Kids and Toddlers By Tiltan Games","o":126,"p":"Free","r":70},{"a":4,"c":14,"e":"Tiltan Games (2013) LTD","g":"14","i":"dino-dot-to-dot-kids-connect_id608803040","n":"Dino Dot To Dot - Kids Connect The Dots - Learning Games By Tiltan Games","o":127,"p":"Free","r":71},{"a":4,"c":15,"e":"Disney","g":"1","i":"the-7d-mine-train_id870601864","n":"The 7D Mine Train","o":3756,"p":"$4.99","r":66},{"a":4.5,"c":15,"e":"Steve Sopoci","g":"6","i":"sponge-jump_id923799051","n":"Sponge Jump","o":84,"p":"Free","r":67},{"a":5,"c":15,"e":"Indygo Media","g":"2","i":"classic-brick-game_id984449941","n":"Classic Brick Game","o":248,"p":"Free","r":68},{"a":4.5,"c":15,"e":"Ulrik Motzfeldt","g":"6","i":"arctic-defences-defend-your_id988727615","n":"' Arctic Defences - Defend Your Island And Beach From The Zombie Dictator","o":44,"p":"Free","r":69},{"a":4,"c":15,"e":"Tiltan Games (2013) LTD","g":"2","i":"puzzle-for-santa-christmas_id581187759","n":"Puzzle for Santa - Christmas Gift HD Puzzles for Kids and Toddler by Tiltan Games","o":243,"p":"Free","r":70},{"a":3.5,"c":15,"e":"KID BABY TODDLER LTD.","g":"14","i":"peekaboo-pets-popping-animals_id507882803","n":"Peekaboo Pets - popping animals toy for kids HD","o":443,"p":"Free","r":71},{"a":4,"c":16,"e":"Happymagenta","g":"1","i":"laser-hell_id852243622","n":"Laser Hell","o":55,"p":"$1.99","r":66,"v":[{"aspect":0.5625,"created_at":"2015-02-14T18:47:24.081Z","duration":146326,"name":"I just got 145 points in #laserhell! Can you beat my score? #happymagenta","source":{"app_id":12409,"id":13976114,"name":"everyplay","page":"https://everyplay.com/videos/13976114"},"thumbnail":"http://static.everyplay.com/everyplay/videos/24591031/13976114/thumbnail_medium.jpg","user":{"id":24591031,"username":"Player24591031"},"video_url":"http://static.everyplay.com/everyplay/videos/24591031/13976114/m31-1500.mp4","views":60},{"aspect":0.5625,"created_at":"2014-10-16T13:53:03.991Z","duration":32485,"name":"I just got 31 points in #laserhell! Can you beat my score? #happymagenta","source":{"app_id":12409,"id":10389619,"name":"everyplay","page":"https://everyplay.com/videos/10389619"},"thumbnail":"http://static.everyplay.com/everyplay/videos/13634816/10389619/thumbnail_medium.jpg","user":{"id":13634816,"username":"zlip"},"video_url":"http://static.everyplay.com/everyplay/videos/13634816/10389619/m31-1500.mp4","views":35},{"aspect":0.6656,"created_at":"2015-02-06T11:47:48.618Z","duration":14518,"name":"OH MY GOD!!!! I haven't played this game in forever an I completely forgot how difficult it was!!","source":{"app_id":12409,"id":13646124,"name":"everyplay","page":"https://everyplay.com/videos/13646124"},"thumbnail":"http://static.everyplay.com/everyplay/videos/24511846/13646124/thumbnail_medium.jpg","user":{"id":24511846,"username":"alpacaking28"},"video_url":"http://static.everyplay.com/everyplay/videos/24511846/13646124/m31-1500.mp4","views":29},{"aspect":0.75,"created_at":"2015-03-20T02:51:21.536Z","duration":6963,"name":"I just got 5 points in #laserhell! Can you beat my score? #happymagenta","source":{"app_id":12409,"id":15104238,"name":"everyplay","page":"https://everyplay.com/videos/15104238"},"thumbnail":"http://static.everyplay.com/everyplay/videos/26482770/15104238/thumbnail_medium.jpg","user":{"id":26482770,"username":"Player26482770"},"video_url":"http://static.everyplay.com/everyplay/videos/26482770/15104238/m31-1500.mp4","views":29},{"aspect":0.75,"created_at":"2015-03-20T07:10:00.608Z","duration":79178,"name":"I just got 78 points in #laserhell! Can you beat my score? #happymagenta","source":{"app_id":12409,"id":15107806,"name":"everyplay","page":"https://everyplay.com/videos/15107806"},"thumbnail":"http://static.everyplay.com/everyplay/videos/26482770/15107806/thumbnail_medium.jpg","user":{"id":26482770,"username":"Player26482770"},"video_url":"http://static.everyplay.com/everyplay/videos/26482770/15107806/m31-1500.mp4","views":26},{"aspect":0.75,"created_at":"2014-12-10T22:37:40.045Z","duration":4465,"name":"Gameplay video!","source":{"app_id":12409,"id":11950153,"name":"everyplay","page":"https://everyplay.com/videos/11950153"},"thumbnail":"http://static.everyplay.com/everyplay/videos/6309428/11950153/thumbnail_medium.jpg","user":{"id":6309428,"username":"Player6309428"},"video_url":"http://static.everyplay.com/everyplay/videos/6309428/11950153/m31-1500.mp4","views":24},{"aspect":0.5625,"created_at":"2014-12-07T22:41:29.804Z","duration":87165,"name":"I just got 86 points in #laserhell! Can you beat my score? #happymagenta","source":{"app_id":12409,"id":11880490,"name":"everyplay","page":"https://everyplay.com/videos/11880490"},"thumbnail":"http://static.everyplay.com/everyplay/videos/24591031/11880490/thumbnail_medium.jpg","user":{"id":24591031,"username":"Player24591031"},"video_url":"http://static.everyplay.com/everyplay/videos/24591031/11880490/m31-1500.mp4","views":24},{"aspect":0.5625,"created_at":"2015-01-28T19:20:37.654Z","duration":114635,"name":"I just got 113 points in #laserhell! Can you beat my score? #happymagenta","source":{"app_id":12409,"id":13353632,"name":"everyplay","page":"https://everyplay.com/videos/13353632"},"thumbnail":"http://static.everyplay.com/everyplay/videos/24591031/13353632/thumbnail_medium.jpg","user":{"id":24591031,"username":"Player24591031"},"video_url":"http://static.everyplay.com/everyplay/videos/24591031/13353632/m31-1500.mp4","views":13},{"aspect":0.75,"created_at":"2014-11-09T15:40:46.907Z","duration":10122,"name":"Gameplay video!","source":{"app_id":12409,"id":11148755,"name":"everyplay","page":"https://everyplay.com/videos/11148755"},"thumbnail":"http://static.everyplay.com/everyplay/videos/23871983/11148755/thumbnail_medium.jpg","user":{"id":23871983,"username":"Player23871983"},"video_url":"http://static.everyplay.com/everyplay/videos/23871983/11148755/m31-1500.mp4","views":9},{"aspect":0.6656,"created_at":"2015-01-23T15:02:50.288Z","duration":7030,"name":"I just got 6 points in #laserhell! Can you beat my score? #happymagenta","source":{"app_id":12409,"id":13220422,"name":"everyplay","page":"https://everyplay.com/videos/13220422"},"thumbnail":"http://static.everyplay.com/everyplay/videos/25333115/13220422/thumbnail_medium.jpg","user":{"id":25333115,"username":"Player25333115"},"video_url":"http://static.everyplay.com/everyplay/videos/25333115/13220422/m31-1500.mp4","views":9},{"aspect":0.5625,"created_at":"2015-06-24T00:20:12.090Z","duration":54281,"name":"I just got 53 points in #LaserHell! Can you beat my score? #happymagenta","source":{"app_id":12409,"id":18045864,"name":"everyplay","page":"https://everyplay.com/videos/18045864"},"thumbnail":"http://static.everyplay.com/everyplay/videos/28162890/18045864/thumbnail_medium.jpg","user":{"id":28162890,"username":"Keir122"},"video_url":"http://static.everyplay.com/everyplay/videos/28162890/18045864/m31-1500.mp4","views":8},{"aspect":0.75,"created_at":"2015-03-20T02:36:44.534Z","duration":11165,"name":"I just got 10 points in #laserhell! Can you beat my score? #happymagenta","source":{"app_id":12409,"id":15103944,"name":"everyplay","page":"https://everyplay.com/videos/15103944"},"thumbnail":"http://static.everyplay.com/everyplay/videos/26482770/15103944/thumbnail_medium.jpg","user":{"id":26482770,"username":"Player26482770"},"video_url":"http://static.everyplay.com/everyplay/videos/26482770/15103944/m31-1500.mp4","views":8},{"aspect":0.5625,"created_at":"2014-11-21T18:45:31.747Z","duration":7080,"name":"I just got 6 points in #laserhell! Can you beat my score? #happymagenta","source":{"app_id":12409,"id":11476423,"name":"everyplay","page":"https://everyplay.com/videos/11476423"},"thumbnail":"http://static.everyplay.com/everyplay/videos/24349422/11476423/thumbnail_medium.jpg","user":{"id":24349422,"username":"Player24349422"},"video_url":"http://static.everyplay.com/everyplay/videos/24349422/11476423/m31-1500.mp4","views":6},{"aspect":0.75,"created_at":"2014-11-12T21:38:55.763Z","duration":39873,"name":"I just got 38 points in #laserhell! Can you beat my score? #happymagenta","source":{"app_id":12409,"id":11257489,"name":"everyplay","page":"https://everyplay.com/videos/11257489"},"thumbnail":"http://static.everyplay.com/everyplay/videos/16552757/11257489/thumbnail_medium.jpg","user":{"id":16552757,"username":"Jodaix"},"video_url":"http://static.everyplay.com/everyplay/videos/16552757/11257489/m31-1500.mp4","views":5},{"aspect":0.75,"created_at":"2014-11-15T22:42:05.495Z","duration":9240,"name":"I just got 8 points in #laserhell! Can you beat my score? #happymagenta","source":{"app_id":12409,"id":11345060,"name":"everyplay","page":"https://everyplay.com/videos/11345060"},"thumbnail":"http://static.everyplay.com/everyplay/videos/24196208/11345060/thumbnail_medium.jpg","user":{"id":24196208,"username":"FranG56"},"video_url":"http://static.everyplay.com/everyplay/videos/24196208/11345060/m31-1500.mp4","views":4},{"aspect":0.5625,"created_at":"2014-12-07T22:37:21.799Z","duration":66941,"name":"Replay from Laser Hell!","source":{"app_id":12409,"id":11880407,"name":"everyplay","page":"https://everyplay.com/videos/11880407"},"thumbnail":"http://static.everyplay.com/everyplay/videos/24591031/11880407/thumbnail_medium.jpg","user":{"id":24591031,"username":"Player24591031"},"video_url":"http://static.everyplay.com/everyplay/videos/24591031/11880407/m31-1500.mp4","views":3}]},{"a":4.5,"c":16,"e":"Sky Tyrannosaur, LLC","g":"6","i":"blowfish-meets-meteor-brick_id792430459","n":"Blowfish Meets Meteor: A Brick-Breaker Adventure","o":87,"p":"Free","r":67},{"a":3.5,"c":16,"e":"Ezone.com","g":"13","i":"crazy-snowboard-holiday-special_id294919686","n":"Crazy Snowboard","o":22352,"p":"$0.99","r":68},{"a":4,"c":16,"e":"Tiltan Games (2013) LTD","g":"10","i":"christmas-toy-party-free-play_id737479986","n":"Christmas Toy Party Free - 9 in 1 Fun Learning Games for kids and toddler","o":122,"p":"Free","r":69},{"a":4,"c":16,"e":"Antti Lehtinen","g":"14","i":"kids-animal-puzzles-best-toddler_id510673136","n":"Kids Animal Puzzles and The Best Toddler Games","o":401,"p":"Free","r":70},{"a":4,"c":16,"e":"Kevin Bradford LLC","g":"14","i":"barnyard-games-for-kids_id498685080","n":"Barnyard Games For Kids","o":378,"p":"Free","r":71},{"a":4.5,"c":17,"e":"Beeline Interactive, Inc.","g":"15","i":"smurf-life_id575225877","n":"Smurf Life","o":13418,"p":"Free","r":66},{"a":4.5,"c":17,"e":"Nostatic Software LLC","g":"15","i":"quiet-please!_id553275179","n":"Quiet, Please!","o":290,"p":"$0.99","r":67},{"a":5,"c":17,"e":"The Game Bakers","g":"15","i":"squids-wild-west_id522145076","n":"Squids Wild West","o":687,"p":"$1.99","r":68},{"a":4,"c":17,"e":"Tiltan Games (2013) LTD","g":"14","i":"dino-does-preschool-math-numbers_id565100820","n":"Dino Does PreSchool Math: Numbers and some ABC Fun Learning Games for Kids and Toddlers","o":106,"p":"Free","r":69},{"a":4.5,"c":17,"e":"Tiltan Games (2013) LTD","g":"2","i":"dino-puzzle-games-jigsaw-puzzles_id561714738","n":"Dino Puzzle Games Free - Dinosaur Jigsaw Puzzles for Kids and Toddler - Tiltan Preschool Learning Games","o":163,"p":"Free","r":70},{"a":3.5,"c":17,"e":"Alexandre Minard","g":"14","i":"my-first-puzzles-alphabet_id408435398","n":"My First Puzzles: Alphabet - An Educational Puzzle Game for Kids for Learning Letter Shapes","o":507,"p":"Free","r":71}]}