{"items_array":[{"a":4.5,"c":66,"e":"Maysalward(MRD)","g":"7","i":"trnyb_id902428862","n":"&#1591;&#1585;&#1606;&#1610;&#1576;","o":150,"p":"Free","r":6},{"a":4,"c":66,"e":"Trivial Technology","g":"7","i":"pinochle-hd_id364543479","n":"Pinochle HD","o":1446,"p":"$1.99","r":7},{"a":4,"c":66,"e":"Quatrian Inc.","g":"12","i":"faceme-backgammon_id407068826","n":"FaceMe Backgammon","o":1575,"p":"$1.99","r":8},{"a":4.5,"c":66,"e":"Jonathan Lanis","g":"6","i":"boost-2_id333191476","n":"Boost 2","o":13666,"p":"$1.99","r":9},{"a":4.5,"c":66,"e":"Eric Snider","g":"12","i":"erics-sudoku-classic-puzzles_id555050672","n":"&#9655;Eric's Sudoku &#8211; Classic Puzzles from Simple to Expert","o":445,"p":"Free","r":10},{"a":4.5,"c":66,"e":"C.H.","g":"2","i":"sudoku_id463419280","n":"&#8882;Sudoku","o":856,"p":"Free","r":11},{"a":4.5,"c":67,"e":"Trivial Technology","g":"7","i":"rummy-500_id963024820","n":"Rummy 500","o":484,"p":"Free","r":6},{"a":4,"c":67,"e":"Byterun","g":"7","i":"canasta-pro_id977944496","n":"Canasta: Pro","o":136,"p":"$2.99","r":7},{"a":4,"c":67,"e":"Adalat Nasibov","g":"7","i":"king-online_id515745371","n":"King Online","o":75,"p":"Free","r":8},{"a":4,"c":67,"e":"JanduSoft S.L.","g":"12","i":"guess-the-character_id428832518","n":"Guess the Character","o":21580,"p":"Free","r":9},{"a":4.5,"c":67,"e":"TicBits Ltd","g":"12","i":"sudoku_id398990729","n":"Sudoku :)","o":13273,"p":"Free","r":10},{"a":4.5,"c":67,"e":"Kristanix Games","g":"12","i":"sudoku-epic_id431473459","n":"Sudoku Epic","o":249,"p":"Free","r":11},{"a":4.5,"c":68,"e":"Antonio Ferraioli","g":"7","i":"rummy-!-solitaire-or-online_id730917430","n":"Rummy ! Solitaire or online with many configuration options - play this card game for free !","o":176,"p":"Free","r":6},{"a":4,"c":68,"e":"Kinkajoo Ltd","g":"12","i":"rummikub_id973113361","n":"Rummikub&#174;","o":168,"p":"$2.99","r":7},{"a":4.5,"c":68,"e":"Adalat Nasibov","g":"12","i":"okey51-online_id504189643","n":"Okey51 Online","o":79,"p":"Free","r":8},{"a":4,"c":68,"e":"Tapps Tecnologia da Informa&#231;&#227;o Ltda.","g":"12","i":"mathdoku+-sudoku-style-math_id559864301","n":"Mathdoku+ Sudoku Style Math &amp; Logic Puzzle Game","o":820,"p":"Free","r":9},{"a":4,"c":68,"e":"Iversoft Solutions","g":"2","i":"pocket-sudoku_id427007128","n":"Pocket Sudoku","o":232,"p":"Free","r":10},{"a":4.5,"c":68,"e":"Thumb Wizards","g":"12","i":"sudoku-packs_id528392366","n":"Sudoku Packs","o":300,"p":"Free","r":11},{"a":5,"c":69,"e":"Jonathan Hill","g":"12","i":"dart-scoreboard-pro_id921865108","n":"Dart Scoreboard Pro","o":20,"p":"$1.99","r":6},{"a":4,"c":69,"e":"9 to 5","g":"12","i":"nummi_id499518978","n":"nummi","o":152,"p":"Free","r":7},{"a":4,"c":69,"e":"Yong Yong Khoo","g":"7","i":"deal-card-game-for-monopoly_id910060884","n":"Deal Card Game for Monopoly","o":46,"p":"Free","r":8},{"a":4.5,"c":69,"e":"Shawn Mottley","g":"12","i":"addictive-mahjong-emoji_id868863054","n":"Addictive Mahjong Emoji","o":474,"p":"Free","r":9},{"a":4.5,"c":69,"e":"REDSTONE - SERVICOS DE INTERNET LTDA - ME","g":"12","i":"casual-mahjong_id824825028","n":"Casual Mahjong","o":64,"p":"Free","r":10},{"a":4.5,"c":69,"e":"G5 Entertainment","g":"12","i":"mahjong-artifacts_id484451282","n":"Mahjong Artifacts","o":107,"p":"Free","r":11},{"a":4,"c":70,"e":"Bitpress, LLC","g":"7","i":"kings-corner-free_id845179811","n":"King's Corner Free","o":161,"p":"Free","r":6},{"a":4.5,"c":70,"e":"Huckleberry BV","g":"12","i":"wordon-hd_id565881351","n":"WordOn HD","o":180,"p":"Free","r":7},{"a":5,"c":70,"e":"Rocket Games","g":"19","i":"bingo-gem-rush-world-jackpot_id905583197","n":"Bingo Gem Rush World Jackpot Blitz: Free Bingo Games Hall Online!","o":121,"p":"Free","r":8},{"a":4.5,"c":70,"e":"Kristanix Games","g":"12","i":"majong-titan-mahjong_id375149734","n":"Majong Titan: Mahjong","o":22868,"p":"Free","r":9},{"a":4.5,"c":70,"e":"DoraLogic","g":"7","i":"majong_id895768565","n":"Majong :)","o":392,"p":"Free","r":10},{"a":4.5,"c":70,"e":"1C Wireless LLC","g":"12","i":"mahjong-3-free_id857769289","n":"Mahjong 3 Free","o":175,"p":"Free","r":11},{"a":4,"c":71,"e":"InfinitApps","g":"7","i":"pyramid-13_id392729799","n":"Pyramid 13","o":170,"p":"$1.99","r":6},{"a":4.5,"c":71,"e":"MAG Interactive","g":"12","i":"quizcross_id581331897","n":"QuizCross","o":2616,"p":"Free","r":7},{"a":4,"c":71,"e":"Dennis Wu","g":"7","i":"play-gin-rummy_id863505097","n":"Play Gin Rummy","o":78,"p":"Free","r":8},{"a":4,"c":71,"e":"Byterun","g":"12","i":"mahjong-tiles_id992367657","n":"Mahjong Tiles","o":542,"p":"Free","r":9},{"a":4,"c":71,"e":"DoraLogic","g":"12","i":"majong-si-chuan_id871405820","n":"Majong &#22235;&#24029;","o":106,"p":"Free","r":10},{"a":4.5,"c":71,"e":"Byterun","g":"12","i":"mahjong-with-words_id975587124","n":"Mahjong with Words","o":84,"p":"Free","r":11}]}